llm_hyperbolic.py
llm_hyperbolic-0.4.9.dist-info/LICENSE
llm_hyperbolic-0.4.9.dist-info/METADATA
llm_hyperbolic-0.4.9.dist-info/WHEEL
llm_hyperbolic-0.4.9.dist-info/entry_points.txt
llm_hyperbolic-0.4.9.dist-info/top_level.txt
llm_hyperbolic-0.4.9.dist-info/RECORD
