Metadata-Version: 2.1
Name: llm-hyperbolic
Version: 0.4.9
Summary: LLM access to Hyperbolic's API
Author: Nick Mystic
License: Apache License
Project-URL: Homepage, https://github.com/ghostofpokemon/llm-hyperbolic
Project-URL: Issues, https://github.com/ghostofpokemon/llm-hyperbolic/issues
Project-URL: CI, https://github.com/ghostofpokemon/llm-hyperbolic/actions
Keywords: llm,ai,hyperbolic,language model,image generation
Classifier: License :: OSI Approved :: Apache Software License
Classifier: Programming Language :: Python :: 3
Classifier: Programming Language :: Python :: 3.8
Classifier: Programming Language :: Python :: 3.9
Classifier: Programming Language :: Python :: 3.10
Classifier: Programming Language :: Python :: 3.11
Classifier: Topic :: Software Development :: Libraries :: Python Modules
Classifier: Topic :: Scientific/Engineering :: Artificial Intelligence
Requires-Python: >=3.8
License-File: LICENSE
Requires-Dist: llm
Requires-Dist: httpx
Requires-Dist: requests
Requires-Dist: pillow
Provides-Extra: test
Requires-Dist: pytest ; extra == 'test'
Requires-Dist: pytest-httpx ; extra == 'test'
